MANIFEST.in
README.rst
docverter.py
setup.py
pydocverter.egg-info/PKG-INFO
pydocverter.egg-info/SOURCES.txt
pydocverter.egg-info/dependency_links.txt
pydocverter.egg-info/pbr.json
pydocverter.egg-info/requires.txt
pydocverter.egg-info/top_level.txt