Metadata-Version: 1.1
Name: pydocverter
Version: 0.0.0
Summary: Client for Docverter document conversion service
Home-page: https://github.com/msabramo/pydocverter
Author: Marc Abramowitz
Author-email: marc@marc-abramowitz.com
License: MIT
Platform: UNKNOWN
Classifier: Development Status :: 4 - Beta
Classifier: Environment :: Console
Classifier: Intended Audience :: Developers
Classifier: License :: OSI Approved :: MIT License
Classifier: Operating System :: POSIX
Classifier: Programming Language :: Python
Classifier: Topic :: Text Processing
Classifier: Topic :: Text Processing :: Filters
